{
  "version": "2.7.17.5d5819b",
  "build_epoch": 1765584000,
  "board": "tlora-c6",
  "mcu": "esp32c6",
  "repo": "meshtastic/firmware",
  "files": [
    {
      "name": "firmware-tlora-c6-2.7.17.5d5819b.elf",
      "md5": "4c2d501743215296cd05145e90d6d978",
      "bytes": 26535888
    },
    {
      "name": "firmware-tlora-c6-2.7.17.5d5819b.bin",
      "md5": "02fb7bae42eaa5f0039d5215eb4b4b9d",
      "bytes": 1581648
    },
    {
      "name": "firmware-tlora-c6-2.7.17.5d5819b.factory.bin",
      "md5": "a245db1510ec952cc8c9a013a2157a81",
      "bytes": 1647184
    },
    {
      "name": "littlefs-tlora-c6-2.7.17.5d5819b.bin",
      "md5": "15754853d316d3af6511cf157426533c",
      "bytes": 1048576
    }
  ],
  "part": [
    {
      "name": "nvs",
      "type": "data",
      "subtype": "nvs",
      "offset": "0x009000",
      "size": "0x005000",
      "flags": ""
    },
    {
      "name": "otadata",
      "type": "data",
      "subtype": "ota",
      "offset": "0x00e000",
      "size": "0x002000",
      "flags": ""
    },
    {
      "name": "app",
      "type": "app",
      "subtype": "ota_0",
      "offset": "0x010000",
      "size": "0x250000",
      "flags": ""
    },
    {
      "name": "flashApp",
      "type": "app",
      "subtype": "ota_1",
      "offset": "0x260000",
      "size": "0x0A0000",
      "flags": ""
    },
    {
      "name": "spiffs",
      "type": "data",
      "subtype": "spiffs",
      "offset": "0x300000",
      "size": "0x100000",
      "flags": ""
    }
  ],
  "has_mui": false,
  "has_inkhud": false
}