{
  "version": "2.7.17.40f1f91",
  "build_epoch": 1765929600,
  "board": "picow",
  "mcu": "rp2040",
  "repo": "meshtastic/firmware",
  "files": [
    {
      "name": "firmware-picow-2.7.17.40f1f91.elf",
      "md5": "d6851bafc03225a05d1b689f096eb7f2",
      "bytes": 11654748
    },
    {
      "name": "firmware-picow-2.7.17.40f1f91.bin",
      "md5": "eb3cc238bdc2f46d0cd15d8d3c431e5e",
      "bytes": 1351432
    },
    {
      "name": "firmware-picow-2.7.17.40f1f91.uf2",
      "md5": "b1ff782dbdcce0da69f3957b4bdac0b3",
      "bytes": 2703360
    }
  ],
  "part": null,
  "has_mui": false,
  "has_inkhud": false
}