{
  "version": "2.7.18.dae4061",
  "build_epoch": 1768262400,
  "platformioTarget": "rak2560",
  "mcu": "nrf52840",
  "repo": "meshtastic/firmware",
  "files": [
    {
      "name": "firmware-rak2560-2.7.18.dae4061.elf",
      "md5": "d0bf2c7192fd3e65b209aa9e48a43d47",
      "bytes": 1359624
    },
    {
      "name": "firmware-rak2560-2.7.18.dae4061.hex",
      "md5": "da37f6b85bada22ac1d349e7bfbb06b5",
      "bytes": 1956175
    },
    {
      "name": "firmware-rak2560-2.7.18.dae4061.uf2",
      "md5": "5418a472c92c055f5418b4bf5577eb9e",
      "bytes": 1391104
    },
    {
      "name": "firmware-rak2560-2.7.18.dae4061-ota.zip",
      "md5": "07f1795a75c8480db298beeadeb6daf2",
      "bytes": 696389
    }
  ],
  "has_mui": false,
  "has_inkhud": false,
  "hwModel": 22,
  "hwModelSlug": "WISMESH_HUB",
  "architecture": "nrf52840",
  "activelySupported": true,
  "displayName": "RAK WisMesh Repeater",
  "supportLevel": 1,
  "images": [
    "rak2560.svg"
  ],
  "tags": [
    "RAK"
  ],
  "requiresDfu": true
}