{
  "version": "2.7.18.dae4061",
  "build_epoch": 1768262400,
  "platformioTarget": "t-watch-s3",
  "mcu": "esp32s3",
  "repo": "meshtastic/firmware",
  "files": [
    {
      "name": "firmware-t-watch-s3-2.7.18.dae4061.elf",
      "md5": "1b48c03dfd066a993eb83c4dd4ec0095",
      "bytes": 22901656
    },
    {
      "name": "firmware-t-watch-s3-2.7.18.dae4061.bin",
      "md5": "8f05984540c0eee3562a9ce7b5e45c0e",
      "bytes": 2161600,
      "part_name": "app0"
    },
    {
      "name": "firmware-t-watch-s3-2.7.18.dae4061.factory.bin",
      "md5": "3124056081a07976062ad8b7ba0c3f5d",
      "bytes": 2227136
    },
    {
      "name": "littlefs-t-watch-s3-2.7.18.dae4061.bin",
      "md5": "b21f1bcb5de354a032eabee9dd486f50",
      "bytes": 3538944,
      "part_name": "spiffs"
    },
    {
      "name": "mt-esp32s3-ota.bin",
      "md5": "5af4e91093b8429751efbeeb4479f180",
      "bytes": 636512,
      "part_name": "app1"
    }
  ],
  "has_mui": false,
  "has_inkhud": false,
  "part": [
    {
      "name": "nvs",
      "type": "data",
      "subtype": "nvs",
      "offset": "0x9000",
      "size": "0x5000",
      "flags": ""
    },
    {
      "name": "otadata",
      "type": "data",
      "subtype": "ota",
      "offset": "0xe000",
      "size": "0x2000",
      "flags": ""
    },
    {
      "name": "app0",
      "type": "app",
      "subtype": "ota_0",
      "offset": "0x10000",
      "size": "0x640000",
      "flags": ""
    },
    {
      "name": "app1",
      "type": "app",
      "subtype": "ota_1",
      "offset": "0x650000",
      "size": "0x640000",
      "flags": ""
    },
    {
      "name": "spiffs",
      "type": "data",
      "subtype": "spiffs",
      "offset": "0xc90000",
      "size": "0x360000",
      "flags": ""
    },
    {
      "name": "coredump",
      "type": "data",
      "subtype": "coredump",
      "offset": "0xFF0000",
      "size": "0x10000",
      "flags": ""
    }
  ],
  "hwModel": 51,
  "hwModelSlug": "T_WATCH_S3",
  "architecture": "esp32-s3",
  "activelySupported": true,
  "displayName": "LILYGO T-Watch S3",
  "supportLevel": 3,
  "images": [
    "t-watch-s3.svg"
  ],
  "tags": [
    "LilyGo"
  ],
  "partitionScheme": "8MB"
}
