{
  "version": "2.7.18.dae4061",
  "build_epoch": 1768262400,
  "platformioTarget": "thinknode_m1-inkhud",
  "mcu": "nrf52840",
  "repo": "meshtastic/firmware",
  "files": [
    {
      "name": "firmware-thinknode_m1-inkhud-2.7.18.dae4061.elf",
      "md5": "4cd34e68a2c7d57a07e7bcbcbf605c1d",
      "bytes": 1094356
    },
    {
      "name": "firmware-thinknode_m1-inkhud-2.7.18.dae4061.hex",
      "md5": "ebc8cf839300f04f34c08c7c769b624e",
      "bytes": 1602283
    },
    {
      "name": "firmware-thinknode_m1-inkhud-2.7.18.dae4061.uf2",
      "md5": "3473ef2b75b263c705a8965af3c017c7",
      "bytes": 1139712
    },
    {
      "name": "firmware-thinknode_m1-inkhud-2.7.18.dae4061-ota.zip",
      "md5": "b677eaf2785e50d56a62644ab32e6940",
      "bytes": 570632
    }
  ],
  "has_mui": false,
  "has_inkhud": true,
  "architecture": "nrf52840",
  "requiresDfu": true,
  "displayName": "thinknode_m1-inkhud",
  "activelySupported": false
}