{
  "version": "2.7.18.3911d5f",
  "build_epoch": 1768435200,
  "platformioTarget": "tlora-c6",
  "mcu": "esp32c6",
  "repo": "meshtastic/firmware",
  "files": [
    {
      "name": "firmware-tlora-c6-2.7.18.3911d5f.elf",
      "md5": "4745db214c195da892904c1183ad860e",
      "bytes": 26943224
    },
    {
      "name": "firmware-tlora-c6-2.7.18.3911d5f.bin",
      "md5": "aeb1d541eeef9055e4b7ee0278dbe6c4",
      "bytes": 1538528,
      "part_name": "app0"
    },
    {
      "name": "firmware-tlora-c6-2.7.18.3911d5f.factory.bin",
      "md5": "89990d1bb67b2e76b58971e73f81a529",
      "bytes": 1604064
    },
    {
      "name": "littlefs-tlora-c6-2.7.18.3911d5f.bin",
      "md5": "2fb8ca16f84992ca7df49e80a8ad4206",
      "bytes": 1048576,
      "part_name": "spiffs"
    },
    {
      "name": "bleota-c3.bin",
      "md5": "20210a70e665e2b61fe1a3bdbd776d25",
      "bytes": 509776,
      "part_name": "app1"
    }
  ],
  "has_mui": false,
  "has_inkhud": false,
  "part": [
    {
      "name": "nvs",
      "type": "data",
      "subtype": "nvs",
      "offset": "0x009000",
      "size": "0x005000",
      "flags": ""
    },
    {
      "name": "otadata",
      "type": "data",
      "subtype": "ota",
      "offset": "0x00e000",
      "size": "0x002000",
      "flags": ""
    },
    {
      "name": "app",
      "type": "app",
      "subtype": "ota_0",
      "offset": "0x010000",
      "size": "0x250000",
      "flags": ""
    },
    {
      "name": "flashApp",
      "type": "app",
      "subtype": "ota_1",
      "offset": "0x260000",
      "size": "0x0A0000",
      "flags": ""
    },
    {
      "name": "spiffs",
      "type": "data",
      "subtype": "spiffs",
      "offset": "0x300000",
      "size": "0x100000",
      "flags": ""
    }
  ],
  "architecture": "esp32-c6",
  "displayName": "tlora-c6",
  "activelySupported": false
}
