{
  "version": "2.7.18.5a81403",
  "build_epoch": 1768348800,
  "platformioTarget": "thinknode_m1-inkhud",
  "mcu": "nrf52840",
  "repo": "meshtastic/firmware",
  "files": [
    {
      "name": "firmware-thinknode_m1-inkhud-2.7.18.5a81403.elf",
      "md5": "990fa0c3e154653e044e643a2e5aca9a",
      "bytes": 1094784
    },
    {
      "name": "firmware-thinknode_m1-inkhud-2.7.18.5a81403.hex",
      "md5": "85bc8ab317c8dc6319a75f01ebe5da32",
      "bytes": 1602111
    },
    {
      "name": "firmware-thinknode_m1-inkhud-2.7.18.5a81403.uf2",
      "md5": "23d72c3867d1f43f119e7fdaae257298",
      "bytes": 1139200
    },
    {
      "name": "firmware-thinknode_m1-inkhud-2.7.18.5a81403-ota.zip",
      "md5": "0ae12276f48e4caa01d3172e20604f76",
      "bytes": 570573
    }
  ],
  "has_mui": false,
  "has_inkhud": true,
  "architecture": "nrf52840",
  "requiresDfu": true,
  "displayName": "thinknode_m1-inkhud",
  "activelySupported": false
}