{
  "version": "2.7.17.b742381",
  "build_epoch": 1765584000,
  "board": "hydra",
  "mcu": "esp32",
  "repo": "meshtastic/firmware",
  "files": [
    {
      "name": "firmware-hydra-2.7.17.b742381.elf",
      "md5": "1aea464e4bda0ef9daedb3f9c4a4deba",
      "bytes": 20546652
    },
    {
      "name": "firmware-hydra-2.7.17.b742381.bin",
      "md5": "e44861b5e2a1454a2ee53d6a8a607da5",
      "bytes": 2210800
    },
    {
      "name": "firmware-hydra-2.7.17.b742381.factory.bin",
      "md5": "714c10a148bc641351d6365f6604bdd9",
      "bytes": 2276336
    },
    {
      "name": "littlefs-hydra-2.7.17.b742381.bin",
      "md5": "4c437608c157f054585b0d7f2795b14a",
      "bytes": 1048576
    }
  ],
  "part": [
    {
      "name": "nvs",
      "type": "data",
      "subtype": "nvs",
      "offset": "0x009000",
      "size": "0x005000",
      "flags": ""
    },
    {
      "name": "otadata",
      "type": "data",
      "subtype": "ota",
      "offset": "0x00e000",
      "size": "0x002000",
      "flags": ""
    },
    {
      "name": "app",
      "type": "app",
      "subtype": "ota_0",
      "offset": "0x010000",
      "size": "0x250000",
      "flags": ""
    },
    {
      "name": "flashApp",
      "type": "app",
      "subtype": "ota_1",
      "offset": "0x260000",
      "size": "0x0A0000",
      "flags": ""
    },
    {
      "name": "spiffs",
      "type": "data",
      "subtype": "spiffs",
      "offset": "0x300000",
      "size": "0x100000",
      "flags": ""
    }
  ],
  "has_mui": false,
  "has_inkhud": false
}